gwf_graph/__init__.py
gwf_graph/main.py
gwf_graph-0.0.4.dist-info/METADATA
gwf_graph-0.0.4.dist-info/WHEEL
gwf_graph-0.0.4.dist-info/entry_points.txt
gwf_graph-0.0.4.dist-info/top_level.txt
gwf_graph-0.0.4.dist-info/RECORD
